authx/__init__.py
authx/apps.py
authx/authX_admin.py
authx/authX_constants.py
authx/authX_decorators.py
authx/authX_forms.py
authx/authX_mixins.py
authx/authX_models.py
authx/authX_settings.py
authx/authX_urls.py
authx/authX_views.py
django_authx_system-0.0.1.dist-info/LICENSE
django_authx_system-0.0.1.dist-info/METADATA
django_authx_system-0.0.1.dist-info/WHEEL
django_authx_system-0.0.1.dist-info/top_level.txt
django_authx_system-0.0.1.dist-info/RECORD
